c19/__init__.py
c19/representations/__init__.py
c19/representations/factorization.py
c19/representations/feature_construction.py
c19/representations/sent_trans.py
c19/representations/statistical.py
c19rep-0.2.dist-info/LICENSE
c19rep-0.2.dist-info/METADATA
c19rep-0.2.dist-info/WHEEL
c19rep-0.2.dist-info/top_level.txt
c19rep-0.2.dist-info/RECORD
