Metadata-Version: 2.1
Name: c19rep
Version: 0.2
Summary: Representations used in COVID19 detection paper.
Home-page: UNKNOWN
Author: Boshko Koloski
Author-email: boshko.koloski@gmail.com
License: UNKNOWN
Keywords: python,covid19 fake news detection,nlp
Platform: UNKNOWN
Classifier: Development Status :: 1 - Planning
Classifier: Intended Audience :: Developers
Classifier: Programming Language :: Python :: 3
Classifier: Operating System :: Unix
License-File: LICENSE
Requires-Dist: nltk (==3.6.1)
Requires-Dist: numpy (==1.20.1)
Requires-Dist: pandas (==1.2.4)
Requires-Dist: scikit-learn (==1.0.1)
Requires-Dist: sentence-transformers
Requires-Dist: scipy (==1.6.2)
